ioshelper/__init__.py
ioshelper/core.py
ioshelper/ida_plugin.py
ioshelper/base/__init__.py
ioshelper/base/reloadable_plugin.py
ioshelper/base/utils.py
ioshelper/plugins/__init__.py
ioshelper/plugins/common/__init__.py
ioshelper/plugins/common/globals.py
ioshelper/plugins/common/run_callback.py
ioshelper/plugins/common/clang_blocks/__init__.py
ioshelper/plugins/common/clang_blocks/analyze_byref_args.py
ioshelper/plugins/common/clang_blocks/block.py
ioshelper/plugins/common/clang_blocks/block_arg_byref.py
ioshelper/plugins/common/clang_blocks/optimize_blocks_init.py
ioshelper/plugins/common/clang_blocks/utils.py
ioshelper/plugins/common/jump_to_string/__init__.py
ioshelper/plugins/common/jump_to_string/jump_to_string.py
ioshelper/plugins/common/outline/__init__.py
ioshelper/plugins/common/outline/outline.py
ioshelper/plugins/common/range_condition/__init__.py
ioshelper/plugins/common/range_condition/range_condition.py
ioshelper/plugins/common/segment_xrefs/__init__.py
ioshelper/plugins/common/segment_xrefs/segment_xrefs.py
ioshelper/plugins/kernelcache/__init__.py
ioshelper/plugins/kernelcache/cpp_vtbl/__init__.py
ioshelper/plugins/kernelcache/cpp_vtbl/cpp_vtbl.py
ioshelper/plugins/kernelcache/func_renamers/__init__.py
ioshelper/plugins/kernelcache/func_renamers/external.py
ioshelper/plugins/kernelcache/func_renamers/func_renamers.py
ioshelper/plugins/kernelcache/func_renamers/handlers.py
ioshelper/plugins/kernelcache/func_renamers/pac_applier.py
ioshelper/plugins/kernelcache/func_renamers/renamer.py
ioshelper/plugins/kernelcache/func_renamers/visitor.py
ioshelper/plugins/kernelcache/generic_calls_fix/__init__.py
ioshelper/plugins/kernelcache/generic_calls_fix/generic_calls_fix.py
ioshelper/plugins/kernelcache/kalloc_type/__init__.py
ioshelper/plugins/kernelcache/kalloc_type/kalloc_type.py
ioshelper/plugins/kernelcache/obj_this/__init__.py
ioshelper/plugins/kernelcache/obj_this/obj_this.py
ioshelper/plugins/objc/__init__.py
ioshelper/plugins/objc/objc_ref/__init__.py
ida_ios_helper-1.0.19.dist-info/METADATA
ida_ios_helper-1.0.19.dist-info/WHEEL
ida_ios_helper-1.0.19.dist-info/licenses/LICENSE
ida_ios_helper-1.0.19.dist-info/RECORD
