Metadata-Version: 2.4
Name: ida-ios-helper
Version: 1.0.19
Summary: IDA Plugin for ease the reversing of iOS' usermode and kernelcache.
Project-URL: Homepage, https://github.com/yoavst/ida-ios-helper
Project-URL: Issues, https://github.com/yoavst/ida-ios-helper/issues
Author-email: Yoav Sternberg <yoav.sternberg@gmail.com>
License-File: LICENSE
Classifier: License :: OSI Approved :: GNU General Public License v3 (GPLv3)
Classifier: Operating System :: OS Independent
Classifier: Programming Language :: Python :: 3
Requires-Python: >=3.10
Requires-Dist: idahelper==1.0.17
